{"nodes": [{"id": "c_users_ericc_source_repos_gauntletci_src_gauntletci_cli_telemetry_telemetryhasher_cs", "label": "TelemetryHasher.cs", "file_type": "code", "source_file": "C:\\Users\\ericc\\source\\repos\\GauntletCI\\src\\GauntletCI.Cli\\Telemetry\\TelemetryHasher.cs", "source_location": "L1"}, {"id": "telemetry_telemetryhasher_telemetryhasher", "label": "TelemetryHasher", "file_type": "code", "source_file": "C:\\Users\\ericc\\source\\repos\\GauntletCI\\src\\GauntletCI.Cli\\Telemetry\\TelemetryHasher.cs", "source_location": "L11"}, {"id": "telemetry_telemetryhasher_telemetryhasher_hash8", "label": ".Hash8()", "file_type": "code", "source_file": "C:\\Users\\ericc\\source\\repos\\GauntletCI\\src\\GauntletCI.Cli\\Telemetry\\TelemetryHasher.cs", "source_location": "L18"}, {"id": "telemetry_telemetryhasher_telemetryhasher_hashrepoasync", "label": ".HashRepoAsync()", "file_type": "code", "source_file": "C:\\Users\\ericc\\source\\repos\\GauntletCI\\src\\GauntletCI.Cli\\Telemetry\\TelemetryHasher.cs", "source_location": "L31"}], "edges": [{"source": "c_users_ericc_source_repos_gauntletci_src_gauntletci_cli_telemetry_telemetryhasher_cs", "target": "cryptography", "relation": "imports", "confidence": "EXTRACTED", "source_file": "C:\\Users\\ericc\\source\\repos\\GauntletCI\\src\\GauntletCI.Cli\\Telemetry\\TelemetryHasher.cs", "source_location": "L2", "weight": 1.0}, {"source": "c_users_ericc_source_repos_gauntletci_src_gauntletci_cli_telemetry_telemetryhasher_cs", "target": "text", "relation": "imports", "confidence": "EXTRACTED", "source_file": "C:\\Users\\ericc\\source\\repos\\GauntletCI\\src\\GauntletCI.Cli\\Telemetry\\TelemetryHasher.cs", "source_location": "L3", "weight": 1.0}, {"source": "c_users_ericc_source_repos_gauntletci_src_gauntletci_cli_telemetry_telemetryhasher_cs", "target": "telemetry_telemetryhasher_telemetryhasher", "relation": "contains", "confidence": "EXTRACTED", "source_file": "C:\\Users\\ericc\\source\\repos\\GauntletCI\\src\\GauntletCI.Cli\\Telemetry\\TelemetryHasher.cs", "source_location": "L11", "weight": 1.0}, {"source": "telemetry_telemetryhasher_telemetryhasher", "target": "telemetry_telemetryhasher_telemetryhasher_hash8", "relation": "method", "confidence": "EXTRACTED", "source_file": "C:\\Users\\ericc\\source\\repos\\GauntletCI\\src\\GauntletCI.Cli\\Telemetry\\TelemetryHasher.cs", "source_location": "L18", "weight": 1.0}, {"source": "telemetry_telemetryhasher_telemetryhasher", "target": "telemetry_telemetryhasher_telemetryhasher_hashrepoasync", "relation": "method", "confidence": "EXTRACTED", "source_file": "C:\\Users\\ericc\\source\\repos\\GauntletCI\\src\\GauntletCI.Cli\\Telemetry\\TelemetryHasher.cs", "source_location": "L31", "weight": 1.0}, {"source": "telemetry_telemetryhasher_telemetryhasher_hashrepoasync", "target": "telemetry_telemetryhasher_telemetryhasher_hash8", "relation": "calls", "confidence": "EXTRACTED", "source_file": "C:\\Users\\ericc\\source\\repos\\GauntletCI\\src\\GauntletCI.Cli\\Telemetry\\TelemetryHasher.cs", "source_location": "L47", "weight": 1.0}], "raw_calls": [{"caller_nid": "telemetry_telemetryhasher_telemetryhasher_hash8", "callee": "IsNullOrEmpty", "is_member_call": true, "source_file": "C:\\Users\\ericc\\source\\repos\\GauntletCI\\src\\GauntletCI.Cli\\Telemetry\\TelemetryHasher.cs", "source_location": "L20"}, {"caller_nid": "telemetry_telemetryhasher_telemetryhasher_hash8", "callee": "HashData", "is_member_call": true, "source_file": "C:\\Users\\ericc\\source\\repos\\GauntletCI\\src\\GauntletCI.Cli\\Telemetry\\TelemetryHasher.cs", "source_location": "L21"}, {"caller_nid": "telemetry_telemetryhasher_telemetryhasher_hash8", "callee": "GetBytes", "is_member_call": true, "source_file": "C:\\Users\\ericc\\source\\repos\\GauntletCI\\src\\GauntletCI.Cli\\Telemetry\\TelemetryHasher.cs", "source_location": "L21"}, {"caller_nid": "telemetry_telemetryhasher_telemetryhasher_hash8", "callee": "ToLowerInvariant", "is_member_call": true, "source_file": "C:\\Users\\ericc\\source\\repos\\GauntletCI\\src\\GauntletCI.Cli\\Telemetry\\TelemetryHasher.cs", "source_location": "L21"}, {"caller_nid": "telemetry_telemetryhasher_telemetryhasher_hash8", "callee": "Trim", "is_member_call": true, "source_file": "C:\\Users\\ericc\\source\\repos\\GauntletCI\\src\\GauntletCI.Cli\\Telemetry\\TelemetryHasher.cs", "source_location": "L21"}, {"caller_nid": "telemetry_telemetryhasher_telemetryhasher_hash8", "callee": "ToLowerInvariant", "is_member_call": true, "source_file": "C:\\Users\\ericc\\source\\repos\\GauntletCI\\src\\GauntletCI.Cli\\Telemetry\\TelemetryHasher.cs", "source_location": "L22"}, {"caller_nid": "telemetry_telemetryhasher_telemetryhasher_hash8", "callee": "ToHexString", "is_member_call": true, "source_file": "C:\\Users\\ericc\\source\\repos\\GauntletCI\\src\\GauntletCI.Cli\\Telemetry\\TelemetryHasher.cs", "source_location": "L22"}, {"caller_nid": "telemetry_telemetryhasher_telemetryhasher_hashrepoasync", "callee": "Start", "is_member_call": true, "source_file": "C:\\Users\\ericc\\source\\repos\\GauntletCI\\src\\GauntletCI.Cli\\Telemetry\\TelemetryHasher.cs", "source_location": "L43"}, {"caller_nid": "telemetry_telemetryhasher_telemetryhasher_hashrepoasync", "callee": "ReadToEndAsync", "is_member_call": true, "source_file": "C:\\Users\\ericc\\source\\repos\\GauntletCI\\src\\GauntletCI.Cli\\Telemetry\\TelemetryHasher.cs", "source_location": "L45"}, {"caller_nid": "telemetry_telemetryhasher_telemetryhasher_hashrepoasync", "callee": "WaitForExitAsync", "is_member_call": true, "source_file": "C:\\Users\\ericc\\source\\repos\\GauntletCI\\src\\GauntletCI.Cli\\Telemetry\\TelemetryHasher.cs", "source_location": "L46"}, {"caller_nid": "telemetry_telemetryhasher_telemetryhasher_hashrepoasync", "callee": "IsNullOrWhiteSpace", "is_member_call": true, "source_file": "C:\\Users\\ericc\\source\\repos\\GauntletCI\\src\\GauntletCI.Cli\\Telemetry\\TelemetryHasher.cs", "source_location": "L47"}]}