{"nodes": [{"id": "c_users_ericc_source_repos_gauntletci_src_gauntletci_corpus_labeling_diffentropyenricher_cs", "label": "DiffEntropyEnricher.cs", "file_type": "code", "source_file": "C:\\Users\\ericc\\source\\repos\\GauntletCI\\src\\GauntletCI.Corpus\\Labeling\\DiffEntropyEnricher.cs", "source_location": "L1"}, {"id": "labeling_diffentropyenricher_diffentropyenricher", "label": "DiffEntropyEnricher", "file_type": "code", "source_file": "C:\\Users\\ericc\\source\\repos\\GauntletCI\\src\\GauntletCI.Corpus\\Labeling\\DiffEntropyEnricher.cs", "source_location": "L12"}, {"id": "labeling_diffentropyenricher_diffentropyenricher_enrichasync", "label": ".EnrichAsync()", "file_type": "code", "source_file": "C:\\Users\\ericc\\source\\repos\\GauntletCI\\src\\GauntletCI.Corpus\\Labeling\\DiffEntropyEnricher.cs", "source_location": "L14"}, {"id": "labeling_diffentropyenricher_diffentropyenricher_computemetrics", "label": ".ComputeMetrics()", "file_type": "code", "source_file": "C:\\Users\\ericc\\source\\repos\\GauntletCI\\src\\GauntletCI.Corpus\\Labeling\\DiffEntropyEnricher.cs", "source_location": "L63"}, {"id": "labeling_diffentropyenricher_diffentropyenricher_countdistinctdirectories", "label": ".CountDistinctDirectories()", "file_type": "code", "source_file": "C:\\Users\\ericc\\source\\repos\\GauntletCI\\src\\GauntletCI.Corpus\\Labeling\\DiffEntropyEnricher.cs", "source_location": "L114"}, {"id": "labeling_diffentropyenricher_diffentropyenricher_countdistinctnamespaces", "label": ".CountDistinctNamespaces()", "file_type": "code", "source_file": "C:\\Users\\ericc\\source\\repos\\GauntletCI\\src\\GauntletCI.Corpus\\Labeling\\DiffEntropyEnricher.cs", "source_location": "L127"}, {"id": "labeling_diffentropyenricher_diffentropyenricher_extractnamespace", "label": ".ExtractNamespace()", "file_type": "code", "source_file": "C:\\Users\\ericc\\source\\repos\\GauntletCI\\src\\GauntletCI.Corpus\\Labeling\\DiffEntropyEnricher.cs", "source_location": "L142"}, {"id": "labeling_diffentropyenricher_diffentropyenricher_computeshannonentropy", "label": ".ComputeShannonEntropy()", "file_type": "code", "source_file": "C:\\Users\\ericc\\source\\repos\\GauntletCI\\src\\GauntletCI.Corpus\\Labeling\\DiffEntropyEnricher.cs", "source_location": "L151"}, {"id": "labeling_diffentropyenricher_diffentropyenricher_writeenrichmentasync", "label": ".WriteEnrichmentAsync()", "file_type": "code", "source_file": "C:\\Users\\ericc\\source\\repos\\GauntletCI\\src\\GauntletCI.Corpus\\Labeling\\DiffEntropyEnricher.cs", "source_location": "L168"}], "edges": [{"source": "c_users_ericc_source_repos_gauntletci_src_gauntletci_corpus_labeling_diffentropyenricher_cs", "target": "models", "relation": "imports", "confidence": "EXTRACTED", "source_file": "C:\\Users\\ericc\\source\\repos\\GauntletCI\\src\\GauntletCI.Corpus\\Labeling\\DiffEntropyEnricher.cs", "source_location": "L2", "weight": 1.0}, {"source": "c_users_ericc_source_repos_gauntletci_src_gauntletci_corpus_labeling_diffentropyenricher_cs", "target": "storage", "relation": "imports", "confidence": "EXTRACTED", "source_file": "C:\\Users\\ericc\\source\\repos\\GauntletCI\\src\\GauntletCI.Corpus\\Labeling\\DiffEntropyEnricher.cs", "source_location": "L3", "weight": 1.0}, {"source": "c_users_ericc_source_repos_gauntletci_src_gauntletci_corpus_labeling_diffentropyenricher_cs", "target": "labeling_diffentropyenricher_diffentropyenricher", "relation": "contains", "confidence": "EXTRACTED", "source_file": "C:\\Users\\ericc\\source\\repos\\GauntletCI\\src\\GauntletCI.Corpus\\Labeling\\DiffEntropyEnricher.cs", "source_location": "L12", "weight": 1.0}, {"source": "labeling_diffentropyenricher_diffentropyenricher", "target": "labeling_diffentropyenricher_diffentropyenricher_enrichasync", "relation": "method", "confidence": "EXTRACTED", "source_file": "C:\\Users\\ericc\\source\\repos\\GauntletCI\\src\\GauntletCI.Corpus\\Labeling\\DiffEntropyEnricher.cs", "source_location": "L14", "weight": 1.0}, {"source": "labeling_diffentropyenricher_diffentropyenricher", "target": "labeling_diffentropyenricher_diffentropyenricher_computemetrics", "relation": "method", "confidence": "EXTRACTED", "source_file": "C:\\Users\\ericc\\source\\repos\\GauntletCI\\src\\GauntletCI.Corpus\\Labeling\\DiffEntropyEnricher.cs", "source_location": "L63", "weight": 1.0}, {"source": "labeling_diffentropyenricher_diffentropyenricher", "target": "labeling_diffentropyenricher_diffentropyenricher_countdistinctdirectories", "relation": "method", "confidence": "EXTRACTED", "source_file": "C:\\Users\\ericc\\source\\repos\\GauntletCI\\src\\GauntletCI.Corpus\\Labeling\\DiffEntropyEnricher.cs", "source_location": "L114", "weight": 1.0}, {"source": "labeling_diffentropyenricher_diffentropyenricher", "target": "labeling_diffentropyenricher_diffentropyenricher_countdistinctnamespaces", "relation": "method", "confidence": "EXTRACTED", "source_file": "C:\\Users\\ericc\\source\\repos\\GauntletCI\\src\\GauntletCI.Corpus\\Labeling\\DiffEntropyEnricher.cs", "source_location": "L127", "weight": 1.0}, {"source": "labeling_diffentropyenricher_diffentropyenricher", "target": "labeling_diffentropyenricher_diffentropyenricher_extractnamespace", "relation": "method", "confidence": "EXTRACTED", "source_file": "C:\\Users\\ericc\\source\\repos\\GauntletCI\\src\\GauntletCI.Corpus\\Labeling\\DiffEntropyEnricher.cs", "source_location": "L142", "weight": 1.0}, {"source": "labeling_diffentropyenricher_diffentropyenricher", "target": "labeling_diffentropyenricher_diffentropyenricher_computeshannonentropy", "relation": "method", "confidence": "EXTRACTED", "source_file": "C:\\Users\\ericc\\source\\repos\\GauntletCI\\src\\GauntletCI.Corpus\\Labeling\\DiffEntropyEnricher.cs", "source_location": "L151", "weight": 1.0}, {"source": "labeling_diffentropyenricher_diffentropyenricher", "target": "labeling_diffentropyenricher_diffentropyenricher_writeenrichmentasync", "relation": "method", "confidence": "EXTRACTED", "source_file": "C:\\Users\\ericc\\source\\repos\\GauntletCI\\src\\GauntletCI.Corpus\\Labeling\\DiffEntropyEnricher.cs", "source_location": "L168", "weight": 1.0}, {"source": "labeling_diffentropyenricher_diffentropyenricher_enrichasync", "target": "labeling_diffentropyenricher_diffentropyenricher_computemetrics", "relation": "calls", "confidence": "EXTRACTED", "source_file": "C:\\Users\\ericc\\source\\repos\\GauntletCI\\src\\GauntletCI.Corpus\\Labeling\\DiffEntropyEnricher.cs", "source_location": "L40", "weight": 1.0}, {"source": "labeling_diffentropyenricher_diffentropyenricher_enrichasync", "target": "labeling_diffentropyenricher_diffentropyenricher_writeenrichmentasync", "relation": "calls", "confidence": "EXTRACTED", "source_file": "C:\\Users\\ericc\\source\\repos\\GauntletCI\\src\\GauntletCI.Corpus\\Labeling\\DiffEntropyEnricher.cs", "source_location": "L42", "weight": 1.0}, {"source": "labeling_diffentropyenricher_diffentropyenricher_computemetrics", "target": "labeling_diffentropyenricher_diffentropyenricher_countdistinctdirectories", "relation": "calls", "confidence": "EXTRACTED", "source_file": "C:\\Users\\ericc\\source\\repos\\GauntletCI\\src\\GauntletCI.Corpus\\Labeling\\DiffEntropyEnricher.cs", "source_location": "L104", "weight": 1.0}, {"source": "labeling_diffentropyenricher_diffentropyenricher_computemetrics", "target": "labeling_diffentropyenricher_diffentropyenricher_countdistinctnamespaces", "relation": "calls", "confidence": "EXTRACTED", "source_file": "C:\\Users\\ericc\\source\\repos\\GauntletCI\\src\\GauntletCI.Corpus\\Labeling\\DiffEntropyEnricher.cs", "source_location": "L105", "weight": 1.0}, {"source": "labeling_diffentropyenricher_diffentropyenricher_computemetrics", "target": "labeling_diffentropyenricher_diffentropyenricher_computeshannonentropy", "relation": "calls", "confidence": "EXTRACTED", "source_file": "C:\\Users\\ericc\\source\\repos\\GauntletCI\\src\\GauntletCI.Corpus\\Labeling\\DiffEntropyEnricher.cs", "source_location": "L106", "weight": 1.0}, {"source": "labeling_diffentropyenricher_diffentropyenricher_countdistinctnamespaces", "target": "labeling_diffentropyenricher_diffentropyenricher_extractnamespace", "relation": "calls", "confidence": "EXTRACTED", "source_file": "C:\\Users\\ericc\\source\\repos\\GauntletCI\\src\\GauntletCI.Corpus\\Labeling\\DiffEntropyEnricher.cs", "source_location": "L132", "weight": 1.0}], "raw_calls": [{"caller_nid": "labeling_diffentropyenricher_diffentropyenricher_enrichasync", "callee": "ThrowIfCancellationRequested", "is_member_call": true, "source_file": "C:\\Users\\ericc\\source\\repos\\GauntletCI\\src\\GauntletCI.Corpus\\Labeling\\DiffEntropyEnricher.cs", "source_location": "L25"}, {"caller_nid": "labeling_diffentropyenricher_diffentropyenricher_enrichasync", "callee": "Combine", "is_member_call": true, "source_file": "C:\\Users\\ericc\\source\\repos\\GauntletCI\\src\\GauntletCI.Corpus\\Labeling\\DiffEntropyEnricher.cs", "source_location": "L27"}, {"caller_nid": "labeling_diffentropyenricher_diffentropyenricher_enrichasync", "callee": "ToLowerInvariant", "is_member_call": true, "source_file": "C:\\Users\\ericc\\source\\repos\\GauntletCI\\src\\GauntletCI.Corpus\\Labeling\\DiffEntropyEnricher.cs", "source_location": "L29"}, {"caller_nid": "labeling_diffentropyenricher_diffentropyenricher_enrichasync", "callee": "ToString", "is_member_call": true, "source_file": "C:\\Users\\ericc\\source\\repos\\GauntletCI\\src\\GauntletCI.Corpus\\Labeling\\DiffEntropyEnricher.cs", "source_location": "L29"}, {"caller_nid": "labeling_diffentropyenricher_diffentropyenricher_enrichasync", "callee": "Exists", "is_member_call": true, "source_file": "C:\\Users\\ericc\\source\\repos\\GauntletCI\\src\\GauntletCI.Corpus\\Labeling\\DiffEntropyEnricher.cs", "source_location": "L33"}, {"caller_nid": "labeling_diffentropyenricher_diffentropyenricher_enrichasync", "callee": "ReadAllLinesAsync", "is_member_call": true, "source_file": "C:\\Users\\ericc\\source\\repos\\GauntletCI\\src\\GauntletCI.Corpus\\Labeling\\DiffEntropyEnricher.cs", "source_location": "L39"}, {"caller_nid": "labeling_diffentropyenricher_diffentropyenricher_enrichasync", "callee": "Invoke", "is_member_call": true, "source_file": "C:\\Users\\ericc\\source\\repos\\GauntletCI\\src\\GauntletCI.Corpus\\Labeling\\DiffEntropyEnricher.cs", "source_location": "L49"}, {"caller_nid": "labeling_diffentropyenricher_diffentropyenricher_computemetrics", "callee": "StartsWith", "is_member_call": true, "source_file": "C:\\Users\\ericc\\source\\repos\\GauntletCI\\src\\GauntletCI.Corpus\\Labeling\\DiffEntropyEnricher.cs", "source_location": "L71"}, {"caller_nid": "labeling_diffentropyenricher_diffentropyenricher_computemetrics", "callee": "IndexOf", "is_member_call": true, "source_file": "C:\\Users\\ericc\\source\\repos\\GauntletCI\\src\\GauntletCI.Corpus\\Labeling\\DiffEntropyEnricher.cs", "source_location": "L74"}, {"caller_nid": "labeling_diffentropyenricher_diffentropyenricher_computemetrics", "callee": "ContainsKey", "is_member_call": true, "source_file": "C:\\Users\\ericc\\source\\repos\\GauntletCI\\src\\GauntletCI.Corpus\\Labeling\\DiffEntropyEnricher.cs", "source_location": "L76"}, {"caller_nid": "labeling_diffentropyenricher_diffentropyenricher_computemetrics", "callee": "StartsWith", "is_member_call": true, "source_file": "C:\\Users\\ericc\\source\\repos\\GauntletCI\\src\\GauntletCI.Corpus\\Labeling\\DiffEntropyEnricher.cs", "source_location": "L84"}, {"caller_nid": "labeling_diffentropyenricher_diffentropyenricher_computemetrics", "callee": "StartsWith", "is_member_call": true, "source_file": "C:\\Users\\ericc\\source\\repos\\GauntletCI\\src\\GauntletCI.Corpus\\Labeling\\DiffEntropyEnricher.cs", "source_location": "L85"}, {"caller_nid": "labeling_diffentropyenricher_diffentropyenricher_computemetrics", "callee": "GetValueOrDefault", "is_member_call": true, "source_file": "C:\\Users\\ericc\\source\\repos\\GauntletCI\\src\\GauntletCI.Corpus\\Labeling\\DiffEntropyEnricher.cs", "source_location": "L87"}, {"caller_nid": "labeling_diffentropyenricher_diffentropyenricher_computemetrics", "callee": "StartsWith", "is_member_call": true, "source_file": "C:\\Users\\ericc\\source\\repos\\GauntletCI\\src\\GauntletCI.Corpus\\Labeling\\DiffEntropyEnricher.cs", "source_location": "L92"}, {"caller_nid": "labeling_diffentropyenricher_diffentropyenricher_computemetrics", "callee": "StartsWith", "is_member_call": true, "source_file": "C:\\Users\\ericc\\source\\repos\\GauntletCI\\src\\GauntletCI.Corpus\\Labeling\\DiffEntropyEnricher.cs", "source_location": "L93"}, {"caller_nid": "labeling_diffentropyenricher_diffentropyenricher_computemetrics", "callee": "GetValueOrDefault", "is_member_call": true, "source_file": "C:\\Users\\ericc\\source\\repos\\GauntletCI\\src\\GauntletCI.Corpus\\Labeling\\DiffEntropyEnricher.cs", "source_location": "L95"}, {"caller_nid": "labeling_diffentropyenricher_diffentropyenricher_computemetrics", "callee": "Sum", "is_member_call": true, "source_file": "C:\\Users\\ericc\\source\\repos\\GauntletCI\\src\\GauntletCI.Corpus\\Labeling\\DiffEntropyEnricher.cs", "source_location": "L103"}, {"caller_nid": "labeling_diffentropyenricher_diffentropyenricher_computemetrics", "callee": "Log2", "is_member_call": true, "source_file": "C:\\Users\\ericc\\source\\repos\\GauntletCI\\src\\GauntletCI.Corpus\\Labeling\\DiffEntropyEnricher.cs", "source_location": "L107"}, {"caller_nid": "labeling_diffentropyenricher_diffentropyenricher_countdistinctdirectories", "callee": "Replace", "is_member_call": true, "source_file": "C:\\Users\\ericc\\source\\repos\\GauntletCI\\src\\GauntletCI.Corpus\\Labeling\\DiffEntropyEnricher.cs", "source_location": "L119"}, {"caller_nid": "labeling_diffentropyenricher_diffentropyenricher_countdistinctdirectories", "callee": "LastIndexOf", "is_member_call": true, "source_file": "C:\\Users\\ericc\\source\\repos\\GauntletCI\\src\\GauntletCI.Corpus\\Labeling\\DiffEntropyEnricher.cs", "source_location": "L120"}, {"caller_nid": "labeling_diffentropyenricher_diffentropyenricher_countdistinctdirectories", "callee": "Add", "is_member_call": true, "source_file": "C:\\Users\\ericc\\source\\repos\\GauntletCI\\src\\GauntletCI.Corpus\\Labeling\\DiffEntropyEnricher.cs", "source_location": "L122"}, {"caller_nid": "labeling_diffentropyenricher_diffentropyenricher_countdistinctnamespaces", "callee": "Add", "is_member_call": true, "source_file": "C:\\Users\\ericc\\source\\repos\\GauntletCI\\src\\GauntletCI.Corpus\\Labeling\\DiffEntropyEnricher.cs", "source_location": "L133"}, {"caller_nid": "labeling_diffentropyenricher_diffentropyenricher_extractnamespace", "callee": "Replace", "is_member_call": true, "source_file": "C:\\Users\\ericc\\source\\repos\\GauntletCI\\src\\GauntletCI.Corpus\\Labeling\\DiffEntropyEnricher.cs", "source_location": "L144"}, {"caller_nid": "labeling_diffentropyenricher_diffentropyenricher_extractnamespace", "callee": "Split", "is_member_call": true, "source_file": "C:\\Users\\ericc\\source\\repos\\GauntletCI\\src\\GauntletCI.Corpus\\Labeling\\DiffEntropyEnricher.cs", "source_location": "L145"}, {"caller_nid": "labeling_diffentropyenricher_diffentropyenricher_computeshannonentropy", "callee": "Log2", "is_member_call": true, "source_file": "C:\\Users\\ericc\\source\\repos\\GauntletCI\\src\\GauntletCI.Corpus\\Labeling\\DiffEntropyEnricher.cs", "source_location": "L161"}, {"caller_nid": "labeling_diffentropyenricher_diffentropyenricher_writeenrichmentasync", "callee": "CreateCommand", "is_member_call": true, "source_file": "C:\\Users\\ericc\\source\\repos\\GauntletCI\\src\\GauntletCI.Corpus\\Labeling\\DiffEntropyEnricher.cs", "source_location": "L172"}, {"caller_nid": "labeling_diffentropyenricher_diffentropyenricher_writeenrichmentasync", "callee": "AddWithValue", "is_member_call": true, "source_file": "C:\\Users\\ericc\\source\\repos\\GauntletCI\\src\\GauntletCI.Corpus\\Labeling\\DiffEntropyEnricher.cs", "source_location": "L181"}, {"caller_nid": "labeling_diffentropyenricher_diffentropyenricher_writeenrichmentasync", "callee": "AddWithValue", "is_member_call": true, "source_file": "C:\\Users\\ericc\\source\\repos\\GauntletCI\\src\\GauntletCI.Corpus\\Labeling\\DiffEntropyEnricher.cs", "source_location": "L182"}, {"caller_nid": "labeling_diffentropyenricher_diffentropyenricher_writeenrichmentasync", "callee": "AddWithValue", "is_member_call": true, "source_file": "C:\\Users\\ericc\\source\\repos\\GauntletCI\\src\\GauntletCI.Corpus\\Labeling\\DiffEntropyEnricher.cs", "source_location": "L183"}, {"caller_nid": "labeling_diffentropyenricher_diffentropyenricher_writeenrichmentasync", "callee": "AddWithValue", "is_member_call": true, "source_file": "C:\\Users\\ericc\\source\\repos\\GauntletCI\\src\\GauntletCI.Corpus\\Labeling\\DiffEntropyEnricher.cs", "source_location": "L184"}, {"caller_nid": "labeling_diffentropyenricher_diffentropyenricher_writeenrichmentasync", "callee": "AddWithValue", "is_member_call": true, "source_file": "C:\\Users\\ericc\\source\\repos\\GauntletCI\\src\\GauntletCI.Corpus\\Labeling\\DiffEntropyEnricher.cs", "source_location": "L185"}, {"caller_nid": "labeling_diffentropyenricher_diffentropyenricher_writeenrichmentasync", "callee": "AddWithValue", "is_member_call": true, "source_file": "C:\\Users\\ericc\\source\\repos\\GauntletCI\\src\\GauntletCI.Corpus\\Labeling\\DiffEntropyEnricher.cs", "source_location": "L186"}, {"caller_nid": "labeling_diffentropyenricher_diffentropyenricher_writeenrichmentasync", "callee": "AddWithValue", "is_member_call": true, "source_file": "C:\\Users\\ericc\\source\\repos\\GauntletCI\\src\\GauntletCI.Corpus\\Labeling\\DiffEntropyEnricher.cs", "source_location": "L187"}, {"caller_nid": "labeling_diffentropyenricher_diffentropyenricher_writeenrichmentasync", "callee": "AddWithValue", "is_member_call": true, "source_file": "C:\\Users\\ericc\\source\\repos\\GauntletCI\\src\\GauntletCI.Corpus\\Labeling\\DiffEntropyEnricher.cs", "source_location": "L188"}, {"caller_nid": "labeling_diffentropyenricher_diffentropyenricher_writeenrichmentasync", "callee": "ExecuteNonQueryAsync", "is_member_call": true, "source_file": "C:\\Users\\ericc\\source\\repos\\GauntletCI\\src\\GauntletCI.Corpus\\Labeling\\DiffEntropyEnricher.cs", "source_location": "L189"}]}