{"nodes": [{"id": "c_users_ericc_source_repos_gauntletci_src_gauntletci_core_fileanalysis_changedfileanalyzer_cs", "label": "ChangedFileAnalyzer.cs", "file_type": "code", "source_file": "C:\\Users\\ericc\\source\\repos\\GauntletCI\\src\\GauntletCI.Core\\FileAnalysis\\ChangedFileAnalyzer.cs", "source_location": "L1"}, {"id": "fileanalysis_changedfileanalyzer_changedfileanalyzer", "label": "ChangedFileAnalyzer", "file_type": "code", "source_file": "C:\\Users\\ericc\\source\\repos\\GauntletCI\\src\\GauntletCI.Core\\FileAnalysis\\ChangedFileAnalyzer.cs", "source_location": "L10"}, {"id": "ichangedfileanalyzer", "label": "IChangedFileAnalyzer", "file_type": "code", "source_file": "", "source_location": ""}, {"id": "fileanalysis_changedfileanalyzer_changedfileanalyzer_analyze", "label": ".Analyze()", "file_type": "code", "source_file": "C:\\Users\\ericc\\source\\repos\\GauntletCI\\src\\GauntletCI.Core\\FileAnalysis\\ChangedFileAnalyzer.cs", "source_location": "L27"}, {"id": "fileanalysis_changedfileanalyzer_changedfileanalyzer_islikelygenerated", "label": ".IsLikelyGenerated()", "file_type": "code", "source_file": "C:\\Users\\ericc\\source\\repos\\GauntletCI\\src\\GauntletCI.Core\\FileAnalysis\\ChangedFileAnalyzer.cs", "source_location": "L148"}], "edges": [{"source": "c_users_ericc_source_repos_gauntletci_src_gauntletci_core_fileanalysis_changedfileanalyzer_cs", "target": "diff", "relation": "imports", "confidence": "EXTRACTED", "source_file": "C:\\Users\\ericc\\source\\repos\\GauntletCI\\src\\GauntletCI.Core\\FileAnalysis\\ChangedFileAnalyzer.cs", "source_location": "L2", "weight": 1.0}, {"source": "c_users_ericc_source_repos_gauntletci_src_gauntletci_core_fileanalysis_changedfileanalyzer_cs", "target": "fileanalysis_changedfileanalyzer_changedfileanalyzer", "relation": "contains", "confidence": "EXTRACTED", "source_file": "C:\\Users\\ericc\\source\\repos\\GauntletCI\\src\\GauntletCI.Core\\FileAnalysis\\ChangedFileAnalyzer.cs", "source_location": "L10", "weight": 1.0}, {"source": "fileanalysis_changedfileanalyzer_changedfileanalyzer", "target": "ichangedfileanalyzer", "relation": "inherits", "confidence": "EXTRACTED", "source_file": "C:\\Users\\ericc\\source\\repos\\GauntletCI\\src\\GauntletCI.Core\\FileAnalysis\\ChangedFileAnalyzer.cs", "source_location": "L10", "weight": 1.0}, {"source": "fileanalysis_changedfileanalyzer_changedfileanalyzer", "target": "fileanalysis_changedfileanalyzer_changedfileanalyzer_analyze", "relation": "method", "confidence": "EXTRACTED", "source_file": "C:\\Users\\ericc\\source\\repos\\GauntletCI\\src\\GauntletCI.Core\\FileAnalysis\\ChangedFileAnalyzer.cs", "source_location": "L27", "weight": 1.0}, {"source": "fileanalysis_changedfileanalyzer_changedfileanalyzer", "target": "fileanalysis_changedfileanalyzer_changedfileanalyzer_islikelygenerated", "relation": "method", "confidence": "EXTRACTED", "source_file": "C:\\Users\\ericc\\source\\repos\\GauntletCI\\src\\GauntletCI.Core\\FileAnalysis\\ChangedFileAnalyzer.cs", "source_location": "L148", "weight": 1.0}, {"source": "fileanalysis_changedfileanalyzer_changedfileanalyzer_analyze", "target": "fileanalysis_changedfileanalyzer_changedfileanalyzer_islikelygenerated", "relation": "calls", "confidence": "EXTRACTED", "source_file": "C:\\Users\\ericc\\source\\repos\\GauntletCI\\src\\GauntletCI.Core\\FileAnalysis\\ChangedFileAnalyzer.cs", "source_location": "L83", "weight": 1.0}], "raw_calls": [{"caller_nid": "fileanalysis_changedfileanalyzer_changedfileanalyzer_analyze", "callee": "IsNullOrEmpty", "is_member_call": true, "source_file": "C:\\Users\\ericc\\source\\repos\\GauntletCI\\src\\GauntletCI.Core\\FileAnalysis\\ChangedFileAnalyzer.cs", "source_location": "L30"}, {"caller_nid": "fileanalysis_changedfileanalyzer_changedfileanalyzer_analyze", "callee": "IsNullOrEmpty", "is_member_call": true, "source_file": "C:\\Users\\ericc\\source\\repos\\GauntletCI\\src\\GauntletCI.Core\\FileAnalysis\\ChangedFileAnalyzer.cs", "source_location": "L35"}, {"caller_nid": "fileanalysis_changedfileanalyzer_changedfileanalyzer_analyze", "callee": "GetExtension", "is_member_call": true, "source_file": "C:\\Users\\ericc\\source\\repos\\GauntletCI\\src\\GauntletCI.Core\\FileAnalysis\\ChangedFileAnalyzer.cs", "source_location": "L57"}, {"caller_nid": "fileanalysis_changedfileanalyzer_changedfileanalyzer_analyze", "callee": "GetExtension", "is_member_call": true, "source_file": "C:\\Users\\ericc\\source\\repos\\GauntletCI\\src\\GauntletCI.Core\\FileAnalysis\\ChangedFileAnalyzer.cs", "source_location": "L73"}, {"caller_nid": "fileanalysis_changedfileanalyzer_changedfileanalyzer_analyze", "callee": "GetExtension", "is_member_call": true, "source_file": "C:\\Users\\ericc\\source\\repos\\GauntletCI\\src\\GauntletCI.Core\\FileAnalysis\\ChangedFileAnalyzer.cs", "source_location": "L89"}, {"caller_nid": "fileanalysis_changedfileanalyzer_changedfileanalyzer_analyze", "callee": "GetExtension", "is_member_call": true, "source_file": "C:\\Users\\ericc\\source\\repos\\GauntletCI\\src\\GauntletCI.Core\\FileAnalysis\\ChangedFileAnalyzer.cs", "source_location": "L100"}, {"caller_nid": "fileanalysis_changedfileanalyzer_changedfileanalyzer_analyze", "callee": "IsNullOrEmpty", "is_member_call": true, "source_file": "C:\\Users\\ericc\\source\\repos\\GauntletCI\\src\\GauntletCI.Core\\FileAnalysis\\ChangedFileAnalyzer.cs", "source_location": "L102"}, {"caller_nid": "fileanalysis_changedfileanalyzer_changedfileanalyzer_analyze", "callee": "Contains", "is_member_call": true, "source_file": "C:\\Users\\ericc\\source\\repos\\GauntletCI\\src\\GauntletCI.Core\\FileAnalysis\\ChangedFileAnalyzer.cs", "source_location": "L118"}, {"caller_nid": "fileanalysis_changedfileanalyzer_changedfileanalyzer_islikelygenerated", "callee": "EndsWith", "is_member_call": true, "source_file": "C:\\Users\\ericc\\source\\repos\\GauntletCI\\src\\GauntletCI.Core\\FileAnalysis\\ChangedFileAnalyzer.cs", "source_location": "L149"}, {"caller_nid": "fileanalysis_changedfileanalyzer_changedfileanalyzer_islikelygenerated", "callee": "EndsWith", "is_member_call": true, "source_file": "C:\\Users\\ericc\\source\\repos\\GauntletCI\\src\\GauntletCI.Core\\FileAnalysis\\ChangedFileAnalyzer.cs", "source_location": "L150"}, {"caller_nid": "fileanalysis_changedfileanalyzer_changedfileanalyzer_islikelygenerated", "callee": "EndsWith", "is_member_call": true, "source_file": "C:\\Users\\ericc\\source\\repos\\GauntletCI\\src\\GauntletCI.Core\\FileAnalysis\\ChangedFileAnalyzer.cs", "source_location": "L151"}]}